{
    "entries": [
        {
            "index": {
                "identity": "NTAzMjEzND",
                "confession": "Hello!",
                "size": "25px",
                "color": "red"
            }
        },
        {
            "index": {
                "identity": "NzM4NDYz",
                "confession": "This is amazing!",
                "size": "30px",
                "color": "white",
                "decoration": "underline",
                "time": "10/25/2021, 9:16:25 AM"
            }
        },
        {
            "index": {
                "identity": "NzM4NDYz",
                "confession": "Hello!",
                "size": "30px",
                "color": "white",
                "decoration": "none",
                "time": "10/25/2021, 9:17:06 AM"
            }
        },
        {
            "index": {
                "identity": "NzM4NDYz",
                "confession": "YO",
                "size": "30px",
                "color": "green",
                "decoration": "none",
                "time": "10/25/2021, 9:17:16 AM"
            }
        },
        {
            "index": {
                "identity": "MzMzMDg2Mz",
                "confession": "Hello from mobile!",
                "size": "30px",
                "color": "white",
                "decoration": "none",
                "time": "10/25/2021, 2:04:30 PM"
            }
        },
        {
            "index": {
                "identity": "NzM4NDYz",
                "confession": "Whats up!",
                "size": "30px",
                "color": "white",
                "decoration": "none",
                "time": "10/25/2021, 5:06:27 PM"
            }
        }
    ]
}